{
    "title": "Anukari Demos",
    "dates": {
        "2025-06-25": "published"
    },
    "categories": [
        "music"
    ],
    "tags": [
        "commission"
    ],
    "contributors": {
        "Popbot": "primary creator",
        "Evan Anukari": "anukari dev"
    },
    "links": {
        "watercolor sc": "https://soundcloud.com/anukari/watercolor-feat-popbot-3",
        "feelin plucky sc": "https://soundcloud.com/anukari/feelin-plucky-feat-popbot-13",
        "anukari homepage": "https://anukari.com/",
        "unused demos playlist": "https://soundcloud.com/pbalt1/sets/demos-v2/s-d0i1UWzvF24?si=eb821296495b4ec69be25bb2f24fa83b"
    },
    "contents": [
        "Watercolor",
        "Feellin Plucky"
    ],
    "audio": [
        "Watercolor.mp3",
        "Feelin Plucky.mp3"
    ]
}